py_hanspell_aideer/__init__.py
py_hanspell_aideer/constants.py
py_hanspell_aideer/response.py
py_hanspell_aideer/spell_checker.py
py_hanspell_aideer-1.2.3.dist-info/LICENSE
py_hanspell_aideer-1.2.3.dist-info/METADATA
py_hanspell_aideer-1.2.3.dist-info/WHEEL
py_hanspell_aideer-1.2.3.dist-info/RECORD
