Metadata-Version: 2.1
Name: py-hanspell-aideer
Version: 1.2.3
Summary: 
Author: antaechan
Author-email: 0627antaechan@gmail.com
Requires-Python: >=3.12,<4.0
Classifier: Programming Language :: Python :: 3
Classifier: Programming Language :: Python :: 3.12
Requires-Dist: cachetools (>=5.3.3,<6.0.0)
Requires-Dist: requests (>=2.31.0,<3.0.0)
